[
  {
    "exerciseID": "LazyVault_Beginner_I",
    "name": "lazy vault",
    "description": "x",
    "category": "x",
    "repetitions": "5 on each side",
    "sets": "1",
    "image": "x",
    "video": "x",
    "xp": "1",
    "workout": "FALSE",
    "movementSpecificChallenge": "TRUE",
    "streetMovementChallenge": "FALSE",
    "singlePlayer": "TRUE",
    "multiPlayer": "FALSE"
  },
  {
    "exerciseID": "Pushups_Beginner_I",
    "name": "pushups",
    "description": "x",
    "category": "x",
    "repetitions": "20",
    "sets": "2",
    "image": "https://firebasestorage.googleapis.com/v0/b/firebaseauth-189918.appspot.com/o/HomeWorkout_Beginner%2Fimg_homeworkout.jpg?alt=media&token=687e83b2-9d9c-4bc6-961e-1360c296bcb9",
    "video": "https://player.vimeo.com/video/249822484",
    "xp": "",
    "workout": "TRUE",
    "movementSpecificChallenge": "FALSE",
    "streetMovementChallenge": "FALSE",
    "singlePlayer": "TRUE",
    "multiPlayer": "FALSE"
  },
  {
    "exerciseID": "Hanging_Beginner_I",
    "name": "hanging",
    "description": "x",
    "category": "x",
    "repetitions": "30 seconds",
    "sets": "5",
    "image": "x",
    "video": "x",
    "xp": "",
    "workout": "TRUE",
    "movementSpecificChallenge": "TRUE",
    "streetMovementChallenge": "FALSE",
    "singlePlayer": "TRUE",
    "multiPlayer": "FALSE"
  },
  {
    "exerciseID": "Precision_Beginner_I",
    "name": "precision",
    "description": "x",
    "category": "x",
    "repetitions": "5 sticks in a row",
    "sets": "1",
    "image": "x",
    "video": "x",
    "xp": "1",
    "workout": "FALSE",
    "movementSpecificChallenge": "TRUE",
    "streetMovementChallenge": "FALSE",
    "singlePlayer": "TRUE",
    "multiPlayer": "TRUE"
  },
  {
    "exerciseID": "Precision_Intermediate_I",
    "name": "precision",
    "description": "x",
    "category": "x",
    "repetitions": "10 sticks in a row",
    "sets": "1",
    "image": "x",
    "video": "x",
    "xp": "1",
    "workout": "FALSE",
    "movementSpecificChallenge": "TRUE",
    "streetMovementChallenge": "FALSE",
    "singlePlayer": "TRUE",
    "multiPlayer": "TRUE"
  },
  {
    "exerciseID": "PistolSquat_Intermediate_I",
    "name": "pistol squat",
    "description": "x",
    "category": "x",
    "repetitions": "15 on each side",
    "sets": "3",
    "image": "x",
    "video": "x",
    "xp": "",
    "workout": "FALSE",
    "movementSpecificChallenge": "FALSE",
    "streetMovementChallenge": "FALSE",
    "singlePlayer": "TRUE",
    "multiPlayer": "FALSE"
  },
  {
    "exerciseID": "Balance_Beginner_I",
    "name": "balance",
    "description": "x",
    "category": "x",
    "repetitions": "1 x across the rail",
    "sets": "5",
    "image": "x",
    "video": "x",
    "xp": "",
    "workout": "FALSE",
    "movementSpecificChallenge": "TRUE",
    "streetMovementChallenge": "FALSE",
    "singlePlayer": "TRUE",
    "multiPlayer": "FALSE"
  }
]